browject/__init__.py
browject/main.py
browject/models.py
browject/utils.py
browject-0.1.5.dist-info/LICENSE.md
browject-0.1.5.dist-info/METADATA
browject-0.1.5.dist-info/WHEEL
browject-0.1.5.dist-info/top_level.txt
browject-0.1.5.dist-info/RECORD
