Metadata-Version: 2.1
Name: browject
Version: 0.1.5
Summary: A Python library to seamlessly access and emulate browser attributes. Ideal for reverse engineering antibots. Powered by TakionAPI for up-to-date browser data.
Home-page: https://github.com/glizzykingdreko/browject
Author: glizzykingdreko
Author-email: glizzykingdreko@protonmail.com
Classifier: Programming Language :: Python :: 3
Classifier: License :: OSI Approved :: MIT License
Classifier: Operating System :: OS Independent
Requires-Python: >=3.6
License-File: LICENSE.md
Requires-Dist: certifi ==2023.7.22
Requires-Dist: charset-normalizer ==3.3.1
Requires-Dist: idna ==3.4
Requires-Dist: requests ==2.31.0
Requires-Dist: urllib3 ==2.0.7
